img_characterize/__init__.py
img_characterize/cli.py
img_characterize/core.py
img_characterize/ranking.py
img_characterize/utils.py
img_characterize-0.3.2.dist-info/LICENSE
img_characterize-0.3.2.dist-info/METADATA
img_characterize-0.3.2.dist-info/WHEEL
img_characterize-0.3.2.dist-info/entry_points.txt
img_characterize-0.3.2.dist-info/top_level.txt
img_characterize-0.3.2.dist-info/RECORD
