Metadata-Version: 2.1
Name: img-characterize
Version: 0.3.2
Summary: Convert images to character art with support for multiple character sets and formats
Home-page: https://github.com/kodu-ai/characterize
Author: Kodu AI
Author-email: info@kodu.ai
Project-URL: Bug Reports, https://github.com/kodu-ai/characterize/issues
Project-URL: Source, https://github.com/kodu-ai/characterize
Project-URL: Documentation, https://github.com/kodu-ai/characterize/blob/main/README.md
Keywords: image processing,ascii art,character art,image conversion,text art
Classifier: Development Status :: 5 - Production/Stable
Classifier: Intended Audience :: Developers
Classifier: Topic :: Multimedia :: Graphics :: Graphics Conversion
Classifier: License :: OSI Approved :: MIT License
Classifier: Programming Language :: Python :: 3
Classifier: Programming Language :: Python :: 3.8
Classifier: Programming Language :: Python :: 3.9
Classifier: Programming Language :: Python :: 3.10
Classifier: Programming Language :: Python :: 3.11
Classifier: Programming Language :: Python :: 3.12
Classifier: Operating System :: OS Independent
Requires-Python: >=3.8
License-File: LICENSE
Requires-Dist: pillow>=10.0.0
Requires-Dist: numpy>=1.24.0
